MANIFEST.in
README.md
setup.cfg
setup.py
flask_secure_headers/.DS_Store
flask_secure_headers/__init__.py
flask_secure_headers/__init__.pyc
flask_secure_headers/core.py
flask_secure_headers/core.pyc
flask_secure_headers/headers.py
flask_secure_headers/headers.pyc
flask_secure_headers.egg-info/PKG-INFO
flask_secure_headers.egg-info/SOURCES.txt
flask_secure_headers.egg-info/dependency_links.txt
flask_secure_headers.egg-info/requires.txt
flask_secure_headers.egg-info/top_level.txt
flask_secure_headers/tests/.DS_Store
flask_secure_headers/tests/__init__.py
flask_secure_headers/tests/__init__.pyc
flask_secure_headers/tests/core_test.py
flask_secure_headers/tests/core_test.pyc
flask_secure_headers/tests/headers_test.py
flask_secure_headers/tests/headers_test.pyc